Metadata-Version: 2.1
Name: PaperLibCollect
Version: 0.1
Summary: Collective python packages from papers
Home-page: https://google.com
Author: Author Name
Author-email: author_email@mail.com
License: The Unlicense
Requires-Python: >3.9,<3.12
